pikatopic
