Metadata-Version: 1.0
Name: pikatopic
Version: 1.0.4
Summary: A convenience layer atop Pika for use with RabbitMQ topic exchanges.
Home-page: http://github.com/AnimationMentor/pikatopic
Author: Reed Wade for Artella.com
Author-email: reed@artella.com
License: MIT
Platform: UNKNOWN
